trufflehog_processor/__init__.py
trufflehog_processor/deduplicator.py
trufflehog_processor/filter.py
trufflehog_processor/get_final_json.py
trufflehog_processor/processor.py
trufflehog_processor-1.0.2.dist-info/METADATA
trufflehog_processor-1.0.2.dist-info/WHEEL
trufflehog_processor-1.0.2.dist-info/top_level.txt
trufflehog_processor-1.0.2.dist-info/RECORD
