Metadata-Version: 2.4
Name: trufflehog-processor
Version: 1.0.2
Summary: Process and deduplicate TruffleHog scan results - filter verified and custom detector findings
Home-page: https://github.com/yourusername/trufflehog-processor
Author: Amit Parjapat
Author-email: your.email@example.com
License-Expression: MIT
Project-URL: Homepage, https://github.com/yourusername/trufflehog-processor
Project-URL: Repository, https://github.com/yourusername/trufflehog-processor
Project-URL: Issues, https://github.com/yourusername/trufflehog-processor/issues
Keywords: trufflehog,security,secrets,scanning,deduplication,filtering
Classifier: Development Status :: 4 - Beta
Classifier: Intended Audience :: Developers
Classifier: Topic :: Security
Classifier: Topic :: Software Development :: Libraries :: Python Modules
Classifier: Programming Language :: Python :: 3
Classifier: Programming Language :: Python :: 3.7
Classifier: Programming Language :: Python :: 3.8
Classifier: Programming Language :: Python :: 3.9
Classifier: Programming Language :: Python :: 3.10
Classifier: Programming Language :: Python :: 3.11
Classifier: Programming Language :: Python :: 3.12
Requires-Python: >=3.7
Dynamic: author-email
Dynamic: home-page
Dynamic: requires-python
